Workbook
Name Aporte_mensal: Simulador!$D$16
Name salario: Simulador!$D$11
Name taxa: Simulador!$D$18
Name taxa_mensal: Simulador!$D$20
Name tempo_de_invest: Simulador!$D$17

Sheet Simulador
B10: Parâmetros
B11: Salário | D11: 5000
B12: Rendimento Carteira | D12: =taxa -> 0.0105
B13: Sugestão de Investimento (25%) | D13: =D11*25% -> 1250
B15: Investimento Mensal
B16: Quanto investir por mês ? | D16: 1000
B17: Por quantos Anos ? | D17: 5
B18: Taxa de rendimento mensal ? | D18: 0.0105
B19: Patrimônio acumulado ? | D19: =FV(taxa,tempo_de_invest*12,Aporte_mensal*-1) -> 82995.584
B20: Dividendos mensais ? | D20: =D19*taxa -> 871.45363
B22: Cenários | C22: Patrimônio | D22: Dividendos
A23: 2 | B23: Investimento por 2 anos | C23: =FV(taxa,$A23*12,Aporte_mensal*-1) -> 27133.981 | D23: =C23*taxa -> 284.9068
A24: 5 | B24: Investimento por 5 anos | C24: =FV(taxa,$A24*12,Aporte_mensal*-1) -> 82995.584 | D24: =C24*taxa -> 871.45363
A25: 10 | B25: Investimento por 10 anos | C25: =FV(taxa,$A25*12,Aporte_mensal*-1) -> 238317.97 | D25: =C25*taxa -> 2502.3387
A26: 20 | B26: Investimento por 20 anos | C26: =FV(taxa,$A26*12,Aporte_mensal*-1) -> 1072988.2 | D26: =C26*taxa -> 11266.376
A27: 30 | B27: Investimento por 30 anos | C27: =FV(taxa,$A27*12,Aporte_mensal*-1) -> 3996286.1 | D27: =C27*taxa -> 41961.004
B29: Perfil de investidor | C29: Moderado
B30: Valor investido por mês | C30: =Aporte_mensal -> 1000
B32: Tipo de FII | C32: Percentual Sugerido | D32: Valores
B33: PAPEL | C33: =_xlfn.XLOOKUP(CONCATENATE($C$29,"-",B33),Apoio!$A:$A,Apoio!$D:$D) -> 0.32 | D33: =C33*$C$30 -> 320
B34: TIJOLO | C34: =_xlfn.XLOOKUP(CONCATENATE($C$29,"-",B34),Apoio!$A:$A,Apoio!$D:$D) -> 0.35 | D34: =C34*$C$30 -> 350
B35: HÍBRIDOS | C35: =_xlfn.XLOOKUP(CONCATENATE($C$29,"-",B35),Apoio!$A:$A,Apoio!$D:$D) -> 0.08 | D35: =C35*$C$30 -> 80
B36: FOFs | C36: =_xlfn.XLOOKUP(CONCATENATE($C$29,"-",B36),Apoio!$A:$A,Apoio!$D:$D) -> 0.05 | D36: =C36*$C$30 -> 50
B37: DESENVOLVIMENTO | C37: =_xlfn.XLOOKUP(CONCATENATE($C$29,"-",B37),Apoio!$A:$A,Apoio!$D:$D) -> 0.1 | D37: =C37*$C$30 -> 100
B38: HOTELARIAS | C38: =_xlfn.XLOOKUP(CONCATENATE($C$29,"-",B38),Apoio!$A:$A,Apoio!$D:$D) -> 0.1 | D38: =C38*$C$30 -> 100
D39: =SUM(D33:D38) -> 1000

Sheet Apoio
A1: CHAVE | B1: PERFIL | C1: TIPO DE FII | D1: %
A2: =CONCATENATE(B2,"-",C2) -> Conservador-PAPEL | B2: Conservador | C2: PAPEL | D2: 0.3
A3: =CONCATENATE(B3,"-",C3) -> Conservador-TIJOLO | B3: Conservador | C3: TIJOLO | D3: 0.5
A4: =CONCATENATE(B4,"-",C4) -> Conservador-HÍBRIDOS | B4: Conservador | C4: HÍBRIDOS | D4: 0.1
A5: =CONCATENATE(B5,"-",C5) -> Conservador-FOFs | B5: Conservador | C5: FOFs | D5: 0.1
A6: =CONCATENATE(B6,"-",C6) -> Conservador-DESENVOLVIMENTO | B6: Conservador | C6: DESENVOLVIMENTO | D6: 0
A7: =CONCATENATE(B7,"-",C7) -> Conservador-HOTELARIAS | B7: Conservador | C7: HOTELARIAS | D7: 0
A8: =CONCATENATE(B8,"-",C8) -> Moderado-PAPEL | B8: Moderado | C8: PAPEL | D8: 0.32
A9: =CONCATENATE(B9,"-",C9) -> Moderado-TIJOLO | B9: Moderado | C9: TIJOLO | D9: 0.35
A10: =CONCATENATE(B10,"-",C10) -> Moderado-HÍBRIDOS | B10: Moderado | C10: HÍBRIDOS | D10: 0.08
A11: =CONCATENATE(B11,"-",C11) -> Moderado-FOFs | B11: Moderado | C11: FOFs | D11: 0.05
A12: =CONCATENATE(B12,"-",C12) -> Moderado-DESENVOLVIMENTO | B12: Moderado | C12: DESENVOLVIMENTO | D12: 0.1
A13: =CONCATENATE(B13,"-",C13) -> Moderado-HOTELARIAS | B13: Moderado | C13: HOTELARIAS | D13: 0.1
... A19: =CONCATENATE(B19,"-",C19) -> Agressivo-HOTELARIAS | B19: Agressivo | C19: HOTELARIAS | D19: 0.1
